[
    {
        "id": 15,
        "timestamp": "2026-02-24 23:49:30",
        "map": "de_mirage",
        "team1": "TEAM_1",
        "team2": "TEAM_2",
        "team1_score": 5,
        "team2_score": 2,
        "total_rounds": 7,
        "players": [
            {
                "name": "Teio",
                "team": "TEAM_1",
                "k": 6,
                "d": 2,
                "a": 0,
                "dmg": 639,
                "entry": 1,
                "clutch": 3,
                "k3": 0,
                "k4": 0,
                "k5": 0
            },
            {
                "name": "nineoneGod",
                "team": "TEAM_2",
                "k": 5,
                "d": 6,
                "a": 1,
                "dmg": 580,
                "entry": 2,
                "clutch": 1,
                "k3": 0,
                "k4": 0,
                "k5": 0
            },
            {
                "name": "ser",
                "team": "TEAM_2",
                "k": 2,
                "d": 6,
                "a": 2,
                "dmg": 245,
                "entry": 0,
                "clutch": 1,
                "k3": 0,
                "k4": 0,
                "k5": 0
            }
        ]
    },
    {
        "id": 14,
        "timestamp": "2026-02-24 23:39:20",
        "map": "de_MIRAGE",
        "team1": "TEAM_1",
        "team2": "TEAM_2",
        "team1_score": 8,
        "team2_score": 13,
        "total_rounds": 21,
        "players": [
            {
                "name": "Teio",
                "team": "TEAM_1",
                "k": 16,
                "d": 13,
                "a": 0,
                "dmg": 1777,
                "entry": 6,
                "clutch": 4,
                "k3": 0,
                "k4": 0,
                "k5": 0
            },
            {
                "name": "nineoneGod",
                "team": "TEAM_2",
                "k": 22,
                "d": 11,
                "a": 1,
                "dmg": 2307,
                "entry": 7,
                "clutch": 7,
                "k3": 0,
                "k4": 0,
                "k5": 0
            },
            {
                "name": "ser",
                "team": "TEAM_2",
                "k": 8,
                "d": 15,
                "a": 6,
                "dmg": 1212,
                "entry": 3,
                "clutch": 3,
                "k3": 0,
                "k4": 0,
                "k5": 0
            }
        ]
    },
    {
        "id": 12,
        "timestamp": "2026-02-23 23:59:20",
        "map": "de_inferno",
        "team1": "TEAM_1",
        "team2": "TEAM_2",
        "team1_score": 19,
        "team2_score": 17,
        "total_rounds": 36,
        "players": [
            {
                "name": "nineoneGod",
                "team": "TEAM_1",
                "k": 23,
                "d": 22,
                "a": 13,
                "dmg": 3028,
                "entry": 4,
                "clutch": 0,
                "k3": 0,
                "k4": 0,
                "k5": 0
            },
            {
                "name": "Eastlotus",
                "team": "TEAM_1",
                "k": 28,
                "d": 25,
                "a": 10,
                "dmg": 3358,
                "entry": 5,
                "clutch": 0,
                "k3": 2,
                "k4": 0,
                "k5": 0
            },
            {
                "name": "ser",
                "team": "TEAM_2",
                "k": 23,
                "d": 23,
                "a": 8,
                "dmg": 2625,
                "entry": 5,
                "clutch": 0,
                "k3": 1,
                "k4": 0,
                "k5": 0
            },
            {
                "name": "Teio",
                "team": "TEAM_2",
                "k": 19,
                "d": 24,
                "a": 6,
                "dmg": 2695,
                "entry": 2,
                "clutch": 1,
                "k3": 2,
                "k4": 0,
                "k5": 0
            }
        ]
    },
    {
        "id": 11,
        "timestamp": "2026-02-23 23:06:30",
        "map": "de_nuke",
        "team1": "TEAM_1",
        "team2": "TEAM_2",
        "team1_score": 5,
        "team2_score": 13,
        "total_rounds": 18,
        "players": [
            {
                "name": "ser",
                "team": "TEAM_1",
                "k": 12,
                "d": 16,
                "a": 3,
                "dmg": 1191,
                "entry": 1,
                "clutch": 1,
                "k3": 1,
                "k4": 0,
                "k5": 0
            },
            {
                "name": "nineoneGod",
                "team": "TEAM_1",
                "k": 16,
                "d": 14,
                "a": 4,
                "dmg": 1610,
                "entry": 4,
                "clutch": 1,
                "k3": 0,
                "k4": 0,
                "k5": 0
            },
            {
                "name": "Eastlotus",
                "team": "TEAM_1",
                "k": 9,
                "d": 15,
                "a": 4,
                "dmg": 888,
                "entry": 0,
                "clutch": 0,
                "k3": 0,
                "k4": 0,
                "k5": 0
            },
            {
                "name": "Teio",
                "team": "TEAM_2",
                "k": 15,
                "d": 11,
                "a": 0,
                "dmg": 1444,
                "entry": 2,
                "clutch": 1,
                "k3": 2,
                "k4": 0,
                "k5": 0
            }
        ]
    },
    {
        "id": 10,
        "timestamp": "2026-02-23 20:40:39",
        "map": "de_dust2",
        "team1": "TEAM_1",
        "team2": "TEAM_2",
        "team1_score": 19,
        "team2_score": 15,
        "total_rounds": 34,
        "players": [
            {
                "name": "nineoneGod",
                "team": "TEAM_1",
                "k": 19,
                "d": 15,
                "a": 0,
                "dmg": 2165,
                "entry": 19,
                "clutch": 19,
                "k3": 0,
                "k4": 0,
                "k5": 0
            },
            {
                "name": "Teio",
                "team": "TEAM_2",
                "k": 15,
                "d": 19,
                "a": 0,
                "dmg": 1894,
                "entry": 15,
                "clutch": 15,
                "k3": 0,
                "k4": 0,
                "k5": 0
            }
        ]
    },
    {
        "id": 9,
        "timestamp": "2026-02-23 15:41:36",
        "map": "de_mirage",
        "team1": "TEAM_1",
        "team2": "TEAM_2",
        "team1_score": 6,
        "team2_score": 13,
        "total_rounds": 19,
        "players": [
            {
                "name": "nineoneGod",
                "team": "TEAM_1",
                "k": 6,
                "d": 15,
                "a": 3,
                "dmg": 953,
                "entry": 4,
                "clutch": 0,
                "k3": 0,
                "k4": 0,
                "k5": 0
            },
            {
                "name": "ser",
                "team": "TEAM_1",
                "k": 13,
                "d": 12,
                "a": 1,
                "dmg": 1156,
                "entry": 3,
                "clutch": 4,
                "k3": 0,
                "k4": 0,
                "k5": 0
            },
            {
                "name": "Teio",
                "team": "TEAM_2",
                "k": 14,
                "d": 8,
                "a": 1,
                "dmg": 1430,
                "entry": 6,
                "clutch": 3,
                "k3": 0,
                "k4": 0,
                "k5": 0
            }
        ]
    },
    {
        "id": 8,
        "timestamp": "2026-02-23 14:27:41",
        "map": "de_INFERNO",
        "team1": "TEAM_1",
        "team2": "TEAM_2",
        "team1_score": 16,
        "team2_score": 14,
        "total_rounds": 30,
        "players": [
            {
                "name": "nineoneGod",
                "team": "TEAM_1",
                "k": 16,
                "d": 14,
                "a": 0,
                "dmg": 1999,
                "entry": 16,
                "clutch": 16,
                "k3": 0,
                "k4": 0,
                "k5": 0
            },
            {
                "name": "Teio",
                "team": "TEAM_2",
                "k": 14,
                "d": 16,
                "a": 0,
                "dmg": 1802,
                "entry": 14,
                "clutch": 14,
                "k3": 0,
                "k4": 0,
                "k5": 0
            }
        ]
    }
]